dbt/adapters/mindsdb/__init__.py
dbt/adapters/mindsdb/__version__.py
dbt/adapters/mindsdb/connections.py
dbt/adapters/mindsdb/impl.py
dbt/include/mindsdb/__init__.py
dbt/include/mindsdb/dbt_project.yml
dbt/include/mindsdb/profile_template.yml
dbt/include/mindsdb/sample_profiles.yml
dbt/include/mindsdb/macros/adapters.sql
dbt/include/mindsdb/macros/catalog.sql
dbt/include/mindsdb/macros/materialization/predictor.sql
dbt/include/mindsdb/macros/materialization/table.sql
dbt/include/mindsdb/macros/materialization/view.sql
dbt_mindsdb-1.0.2.dist-info/METADATA
dbt_mindsdb-1.0.2.dist-info/WHEEL
dbt_mindsdb-1.0.2.dist-info/top_level.txt
dbt_mindsdb-1.0.2.dist-info/RECORD
