Metadata-Version: 2.1
Name: dbt-mindsdb
Version: 1.0.2
Summary: The dbt adapter plugin for connecting to MindsDB
Home-page: https://github.com/mindsdb/dbt-mindsdb
Author: MindsDB Inc
Author-email: admin@mindsdb.com
Requires-Dist: dbt-core (==1.0.1)
Requires-Dist: mysql-connector-python (~=8.0.22)
